pysqlscribe/__init__.py
pysqlscribe/aggregate_functions.py
pysqlscribe/alias.py
pysqlscribe/column.py
pysqlscribe/env_utils.py
pysqlscribe/exceptions.py
pysqlscribe/functions.py
pysqlscribe/protocols.py
pysqlscribe/query.py
pysqlscribe/regex_patterns.py
pysqlscribe/scalar_functions.py
pysqlscribe/schema.py
pysqlscribe/table.py
pysqlscribe/ast/__init__.py
pysqlscribe/ast/base.py
pysqlscribe/ast/joins.py
pysqlscribe/ast/nodes.py
pysqlscribe/dialects/__init__.py
pysqlscribe/dialects/base.py
pysqlscribe/dialects/mysql.py
pysqlscribe/dialects/oracle.py
pysqlscribe/dialects/postgres.py
pysqlscribe/dialects/sqlite.py
pysqlscribe/renderers/__init__.py
pysqlscribe/renderers/base.py
pysqlscribe/renderers/mysql.py
pysqlscribe/renderers/oracle.py
pysqlscribe/renderers/postgres.py
pysqlscribe/renderers/sqlite.py
pysqlscribe/utils/__init__.py
pysqlscribe/utils/ddl_loader.py
pysqlscribe/utils/ddl_parser.py
pysqlscribe-0.10.1.dist-info/METADATA
pysqlscribe-0.10.1.dist-info/WHEEL
pysqlscribe-0.10.1.dist-info/licenses/LICENSE
pysqlscribe-0.10.1.dist-info/RECORD
