Metadata-Version: 2.4
Name: pysqlscribe
Version: 0.10.1
Summary: A simple Python Library for building relational database queries using objects
Project-URL: Source code, https://github.com/danielenricocahall/pysqlscribe
Author-email: Daniel Cahall <danielenricocahall@gmail.com>
License-File: LICENSE
Requires-Python: >=3.11
